sms4jawaly_py/__init__.py
sms4jawaly_py/models.py
sms4jawaly_py/sms_gateway.py
sms4jawaly_py-1.0.4.dist-info/METADATA
sms4jawaly_py-1.0.4.dist-info/WHEEL
sms4jawaly_py-1.0.4.dist-info/top_level.txt
sms4jawaly_py-1.0.4.dist-info/RECORD
